Metadata-Version: 2.1
Name: odoo12-addon-stock-picking-package-preparation-line
Version: 12.0.1.0.2
Summary: Stock Picking Package Preparation Line
Home-page: https://github.com/OCA/stock-logistics-workflow12.0/stock_picking_package_preparation_line
Author: Apulia Software srl, Odoo Italia Network, Odoo Community Association (OCA)
Author-email: support@odoo-community.org
License: AGPL-3
Platform: UNKNOWN
Classifier: Programming Language :: Python
Classifier: Framework :: Odoo
Classifier: Framework :: Odoo :: 12.0
Classifier: License :: OSI Approved :: GNU Affero General Public License v3
Requires-Python: >=3.5
Requires-Dist: odoo12-addon-stock-picking-package-preparation
Requires-Dist: odoo (<12.1dev,>=12.0a)
